prcolor/__init__.py
prcolor/color.py
prcolor-0.1.43.dist-info/LICENSE
prcolor-0.1.43.dist-info/METADATA
prcolor-0.1.43.dist-info/WHEEL
prcolor-0.1.43.dist-info/top_level.txt
prcolor-0.1.43.dist-info/RECORD
