Metadata-Version: 2.1
Name: prcolor
Version: 0.1.43
Summary: Color your print()
Home-page: https://github.com/Rashe/p_color
Author: Rashe
License: UNKNOWN
Platform: UNKNOWN
